{
  "15-to-16": {
    "from": "postgres:16-bookworm",
    "new": "16",
    "old": "15",
    "version": "15.4-2.pgdg120+1"
  },
  "14-to-16": {
    "from": "postgres:16-bookworm",
    "new": "16",
    "old": "14",
    "version": "14.9-1.pgdg120+1"
  },
  "13-to-16": {
    "from": "postgres:16-bookworm",
    "new": "16",
    "old": "13",
    "version": "13.12-1.pgdg120+1"
  },
  "12-to-16": {
    "from": "postgres:16-bookworm",
    "new": "16",
    "old": "12",
    "version": "12.16-1.pgdg120+1"
  },
  "11-to-16": {
    "from": "postgres:16-bookworm",
    "new": "16",
    "old": "11",
    "version": "11.21-1.pgdg120+1"
  },
  "14-to-15": {
    "from": "postgres:15-bookworm",
    "new": "15",
    "old": "14",
    "version": "14.9-1.pgdg120+1"
  },
  "13-to-15": {
    "from": "postgres:15-bookworm",
    "new": "15",
    "old": "13",
    "version": "13.12-1.pgdg120+1"
  },
  "12-to-15": {
    "from": "postgres:15-bookworm",
    "new": "15",
    "old": "12",
    "version": "12.16-1.pgdg120+1"
  },
  "11-to-15": {
    "from": "postgres:15-bookworm",
    "new": "15",
    "old": "11",
    "version": "11.21-1.pgdg120+1"
  },
  "13-to-14": {
    "from": "postgres:14-bookworm",
    "new": "14",
    "old": "13",
    "version": "13.12-1.pgdg120+1"
  },
  "12-to-14": {
    "from": "postgres:14-bookworm",
    "new": "14",
    "old": "12",
    "version": "12.16-1.pgdg120+1"
  },
  "11-to-14": {
    "from": "postgres:14-bookworm",
    "new": "14",
    "old": "11",
    "version": "11.21-1.pgdg120+1"
  },
  "12-to-13": {
    "from": "postgres:13-bookworm",
    "new": "13",
    "old": "12",
    "version": "12.16-1.pgdg120+1"
  },
  "11-to-13": {
    "from": "postgres:13-bookworm",
    "new": "13",
    "old": "11",
    "version": "11.21-1.pgdg120+1"
  },
  "11-to-12": {
    "from": "postgres:12-bookworm",
    "new": "12",
    "old": "11",
    "version": "11.21-1.pgdg120+1"
  }
}
